{
  "nameList":[
    {
      "name":"1"
    },
    {
      "name":"11"
    },
    {
      "name":"111"
    },
    {
      "name":"1111"
    },
    {
      "name":"11111"
    },
    {
      "name":"111111"
    },
    {
      "name":"1111111"
    },
    {
      "name":"11111111"
    },
    {
      "name":"111111111"
    },
    {
      "name":"1111111111"
    },
    {
      "name":"11111111111"
    },
    {
      "name":"111111111111"
    },
    {
      "name":"1111111111111"
    },
    {
      "name":"11111111111111"
    },
    {
      "name":"111111111111111"
    }
  ]
}
